hlpj/__init__.py
hlpj/__main__.py
hlpj/config.py
hlpj/menu.py
hlpj/add_txn/TxnAsk.py
hlpj/add_txn/TxnBase.py
hlpj/add_txn/TxnPosting.py
hlpj/add_txn/__init__.py
hlpj/add_txn/__main__.py
hlpj/add_txn/add_txn.py
hlpj/add_txn/ask.py
hlpj/add_txn/hledger-iadd
hlpj/add_txn/txn_lib.py
hlpj/add_txn/validation.py
hlpj/airbnb/__init__.py
hlpj/airbnb/airbnb_import.py
hlpj/airbnb/airbnb_transf.py
hlpj/airbnb/desp_apto.py
hlpj/base/__init__.py
hlpj/base/config.py
hlpj/base/editar.py
hlpj/base/email_send.py
hlpj/base/helpers.py
hlpj/base/hledger_types.py
hlpj/base/recorr.py
hlpj/base/vc.py
hlpj/base/webdav.py
hlpj/contab/__init__.py
hlpj/contab/contab.py
hlpj/contab/hl_contab.py
hlpj/contab/hlpj_closing.sh
hlpj/contab/imp.py
hlpj/financeiro/__init__.py
hlpj/financeiro/add_conciliacao.py
hlpj/financeiro/atrasos.py
hlpj/financeiro/conciliacao.py
hlpj/financeiro/recorr_cp.py
hlpj/financeiro/relatorios.py
hlpj/financeiro/saldos.py
hlpj/financeiro/transacoes.py
hlpj/financeiro/ult_conciliacao.py
hlpj/gestao/__init__.py
hlpj/gestao/controle.py
hlpj/gestao/info.py
hlpj/locacao/__init__.py
hlpj/locacao/atrasados.py
hlpj/locacao/eventos.py
hlpj/locacao/fatura.py
hlpj/locacao/recorr_cr.py
hlpj/locacao/val_locacoes.py
hlpj/templates/fatura.jinja2
hlpj/templates/logo.png
hlpj-0.0.1.data/scripts/hledger-iadd
hlpj-0.0.1.data/scripts/hlpj_closing.sh
hlpj-0.0.1.dist-info/METADATA
hlpj-0.0.1.dist-info/WHEEL
hlpj-0.0.1.dist-info/entry_points.txt
hlpj-0.0.1.dist-info/top_level.txt
hlpj-0.0.1.dist-info/RECORD
