Metadata-Version: 2.1
Name: hlpj
Version: 0.0.1
Author: Eduardo
Author-email: author@example.com
Requires-Python: <4,>=3.5
Requires-Dist: python-dateutil
Requires-Dist: questionary
Requires-Dist: numpy
Requires-Dist: pandas
Requires-Dist: tabulate
Requires-Dist: pdfkit
Requires-Dist: openpyxl
Requires-Dist: jinja2
Requires-Dist: holidays
Requires-Dist: pydantic
Requires-Dist: blessed
Requires-Dist: webdavclient3
